pysetenv/__init__.py
pysetenv/version.py
pysetenv-1.0.1.dist-info/LICENSE
pysetenv-1.0.1.dist-info/METADATA
pysetenv-1.0.1.dist-info/WHEEL
pysetenv-1.0.1.dist-info/entry_points.txt
pysetenv-1.0.1.dist-info/top_level.txt
pysetenv-1.0.1.dist-info/RECORD
