Metadata-Version: 2.1
Name: pysetenv
Version: 1.0.1
Summary: A simple tool to set environment variables before running a command
Home-page: https://github.com/jimporter/pysetenv
Author: Jim Porter
Author-email: itsjimporter@gmail.com
License: BSD
Keywords: set environment variables
Platform: UNKNOWN
Classifier: Development Status :: 5 - Production/Stable
Classifier: Intended Audience :: Developers
Classifier: Topic :: Utilities
Classifier: License :: OSI Approved :: BSD License
Classifier: Programming Language :: Python :: 2
Classifier: Programming Language :: Python :: 2.7
Classifier: Programming Language :: Python :: 3
Classifier: Programming Language :: Python :: 3.5
Classifier: Programming Language :: Python :: 3.6
Classifier: Programming Language :: Python :: 3.7
Provides-Extra: dev
Requires-Dist: coverage ; extra == 'dev'
Requires-Dist: flake8 (>=3.0) ; extra == 'dev'
Requires-Dist: pypandoc ; extra == 'dev'
Provides-Extra: test
Requires-Dist: coverage ; extra == 'test'
Requires-Dist: flake8 (>=3.0) ; extra == 'test'
